MANIFEST.in
README.md
requirements.txt
setup.cfg
setup.py
flow/__init__.py
flow/conditioner.py
flow/flow.py
flow/modules.py
flow/prior.py
flow/training.py
flow/transformer.py
flow/utils.py
flow_torch.egg-info/PKG-INFO
flow_torch.egg-info/SOURCES.txt
flow_torch.egg-info/dependency_links.txt
flow_torch.egg-info/requires.txt
flow_torch.egg-info/top_level.txt