Metadata-Version: 2.1
Name: flow-torch
Version: 0.1
Summary: Normalizing Flow models in PyTorch
Home-page: https://github.com/aparafita/flow
Author: Álvaro Parafita
Author-email: parafita.alvaro@gmail.com
License: MIT
Download-URL: https://github.com/aparafita/flow/archive/v0.1.tar.gz
Keywords: flow,density,estimation,sampling,probability,distribution
Platform: UNKNOWN
Classifier: Development Status :: 3 - Alpha
Classifier: Intended Audience :: Science/Research
Classifier: Topic :: Scientific/Engineering :: Artificial Intelligence
Classifier: License :: OSI Approved :: MIT License
Classifier: Programming Language :: Python :: 3
Classifier: Programming Language :: Python :: 3.6
Classifier: Operating System :: OS Independent
